paramparse.py
docstring_parser_custom/__init__.py
docstring_parser_custom/common.py
docstring_parser_custom/google.py
docstring_parser_custom/numpydoc.py
docstring_parser_custom/parser.py
docstring_parser_custom/rest.py
docstring_parser_custom/styles.py
docstring_parser_custom/tests/__init__.py
docstring_parser_custom/tests/test_google.py
docstring_parser_custom/tests/test_numpydoc.py
docstring_parser_custom/tests/test_parser.py
docstring_parser_custom/tests/test_rest.py
paramparse-1.9.0.dist-info/LICENSE
paramparse-1.9.0.dist-info/METADATA
paramparse-1.9.0.dist-info/WHEEL
paramparse-1.9.0.dist-info/top_level.txt
paramparse-1.9.0.dist-info/RECORD
