Metadata-Version: 2.1
Name: paramparse
Version: 1.9.0
Summary: argparse wrapper to allow hierarchically nested class based parameters
Home-page: https://github.com/abhineet123/paramparse
Author: Abhineet Singh
Author-email: abhineet.iiita@gmail.com
License: UNKNOWN
Platform: UNKNOWN
Classifier: Programming Language :: Python
Classifier: License :: OSI Approved :: MIT License
Classifier: Operating System :: OS Independent
Requires-Python: >3.5.2
